<DOMSymbolItem xmlns:xsi="http://www.w3.org/2001/XMLSchema-instance" xmlns="http://ns.adobe.com/xfl/2008/" name="kara_txt_diabetes" itemID="565bb731-0002a285" lastModified="1448851319">
  <timeline>
    <DOMTimeline name="kara_txt_diabetes" currentFrame="2">
      <layers>
        <DOMLayer name="Layer 2" color="#9933CC" current="true" isSelected="true">
          <frames>
            <DOMFrame index="0" keyMode="9728">
              <Framescript language="JavaScript">
                <script><![CDATA[changeSymbolToLang(this);]]></script>
              </Framescript>
              <elements/>
            </DOMFrame>
            <DOMFrame index="1" name="en" labelType="name" keyMode="9728">
              <elements/>
            </DOMFrame>
            <DOMFrame index="2" name="es" labelType="name" keyMode="9728">
              <elements/>
            </DOMFrame>
          </frames>
        </DOMLayer>
        <DOMLayer name="Layer 1" color="#4F80FF">
          <frames>
            <DOMFrame index="0" keyMode="9728">
              <elements>
                <DOMGroup>
                  <matrix>
                    <Matrix tx="-24.05" ty="-429.05"/>
                  </matrix>
                  <members>
                    <DOMShape>
                      <matrix>
                        <Matrix tx="-24.05" ty="-429.05"/>
                      </matrix>
                      <fills>
                        <FillStyle index="1">
                          <SolidColor color="#303030"/>
                        </FillStyle>
                      </fills>
                      <edges>
                        <Edge fillStyle0="1" edges="!1662 8707S1[1632 8726 1615 8757!1615 8757|1610 8757!1610 8757|1595 8695!1595 8695|1518 8695!1518 8695|1518 9066!1518 9066|1619 9066!1619 9066|1619 8877!1619 8877[1619 8832 1647 8807!1647 8807[1674 8782 1722 8782!1722 8782|1752 8786!1752
 8786|1760 8691!1760 8691|1725 8688!1725 8688[1691 8688 1662 8707!2133 9066|2133 8819!2133 8819[2133 8752 2093 8720!2093 8720[2053 8687 1978 8687!1978 8687[1900 8687 1836 8721!1836 8721|1870 8789!1870 8789[1930 8762 1974 8762!1974 8762
[2032 8762 2032 8819!2032 8819|2032 8835!2032 8835|1968 8837!1968 8837[1884 8840 1843 8868!1843 8868[1802 8896 1802 8955!1802 8955[1802 9012 1832 9042!1832 9042[1863 9073 1916 9073!1916 9073[1960 9073 1987 9060!1987 9060[2014 9048 2040
 9016!2040 9016|2042 9016!2042 9016|2062 9066!2062 9066|2133 9066!2032 8925[2032 8958 2011 8978!2011 8978[1990 8999 1955 8999!1955 8999[1905 8999 1905 8956!1905 8956[1905 8926 1927 8911!1927 8911[1949 8897 1993 8895!1993 8895|2032 8894
!2032 8894|2032 8925!2131 9428[2143 9425 2156 9419!2156 9419|2156 9396!2156 9396[2129 9407 2102 9407!2102 9407[2076 9407 2061 9392!2061 9392[2047 9376 2046 9346!2046 9346|2164 9346!2164 9346|2164 9330!2164 9330[2164 9295 2145 9274!2145
 9274[2126 9253 2094 9253!2094 9253[2060 9253 2039 9277!2039 9277[2019 9301 2019 9343!2019 9343[2019 9384 2041 9407!2041 9407[2063 9430 2101 9430!2101 9430[2118 9430 2131 9428!2125 9287[2136 9300 2136 9325!2136 9325|2046 9325!2046 9325
[2049 9301 2061 9288!2061 9288[2073 9274 2094 9274!2094 9274[2114 9274 2125 9287!2307 9352[2297 9341 2266 9330!2266 9330[2244 9321 2236 9317!2236 9317[2228 9313 2225 9308!2225 9308[2221 9303 2221 9296!2221 9296[2221 9286 2231 9280!2231
 9280[2240 9274 2258 9274!2258 9274[2279 9274 2305 9285!2305 9285|2314 9264!2314 9264[2288 9253 2260 9253!2260 9253[2231 9253 2214 9265!2214 9265[2197 9277 2197 9298!2197 9298[2197 9310 2202 9318!2202 9318[2206 9326 2217 9333!2217 9333
[2227 9340 2250 9349!2250 9349[2276 9358 2284 9365!2284 9365[2293 9372 2293 9382!2293 9382[2293 9396 2282 9402!2282 9402[2271 9409 2251 9409!2251 9409[2238 9409 2224 9405!2224 9405[2209 9402 2197 9395!2197 9395|2197 9419!2197 9419[2216
 9430 2250 9430!2250 9430[2282 9430 2300 9417!2300 9417[2318 9404 2318 9380!2318 9380[2318 9363 2307 9352!1840 9428[1852 9425 1865 9419!1865 9419|1865 9396!1865 9396[1838 9407 1811 9407!1811 9407[1785 9407 1770 9392!1770 9392[1756 9376
 1755 9346!1755 9346|1873 9346!1873 9346|1873 9330!1873 9330[1873 9295 1854 9274!1854 9274[1835 9253 1803 9253!1803 9253[1769 9253 1748 9277!1748 9277[1728 9301 1728 9343!1728 9343[1728 9384 1750 9407!1750 9407[1772 9430 1810 9430!1810
 9430[1827 9430 1840 9428!1567 9279|1566 9279!1566 9279|1567 9184!1567 9184|1542 9184!1542 9184|1542 9427!1542 9427|1560 9427!1560 9427|1566 9405!1566 9405|1567 9405!1567 9405[1577 9418 1591 9424!1591 9424[1604 9430 1621 9430!1621 9430
[1655 9430 1674 9407!1674 9407[1692 9383 1692 9341!1692 9341[1692 9299 1674 9276!1674 9276[1655 9253 1621 9253!1621 9253[1586 9253 1567 9279!1654 9291[1665 9307 1665 9341!1665 9341[1665 9374 1654 9391!1654 9391[1642 9408 1618 9408!1618
 9408[1592 9408 1579 9393!1579 9393[1567 9377 1567 9341!1567 9341[1567 9305 1579 9290!1579 9290[1591 9275 1617 9275!1617 9275[1642 9275 1654 9291!1834 9287[1845 9300 1845 9325!1845 9325|1755 9325!1755 9325[1758 9301 1770 9288!1770 9288
[1782 9274 1803 9274!1803 9274[1823 9274 1834 9287!1952 9400[1944 9392 1944 9377!1944 9377|1944 9276!1944 9276|1994 9276!1994 9276|1994 9256!1994 9256|1944 9256!1944 9256|1944 9216!1944 9216|1929 9216!1929 9216|1918 9253!1918 9253|1894
 9263!1894 9263|1894 9276!1894 9276|1918 9276!1918 9276|1918 9378!1918 9378[1918 9430 1968 9430!1968 9430|1983 9429!1983 9429|1995 9425!1995 9425|1995 9406!1995 9406|1985 9408!1985 9408|1972 9409!1972 9409[1959 9409 1952 9400!885 8795
|1054 8581!1054 8581|940 8581!940 8581|768 8803!768 8803|768 8581!768 8581|665 8581!665 8581|665 9066!665 9066|768 9066!768 9066|768 8893!768 8893|812 8861!812 8861|939 9066!939 9066|1056 9066!1056 9066|885 8795!1415 9066|1415 8819!1415
 8819[1415 8752 1375 8720!1375 8720[1335 8687 1260 8687!1260 8687[1182 8687 1118 8721!1118 8721|1152 8789!1152 8789[1212 8762 1256 8762!1256 8762[1314 8762 1314 8819!1314 8819|1314 8835!1314 8835|1250 8837!1250 8837[1166 8840 1125 8868
!1125 8868[1084 8896 1084 8955!1084 8955[1084 9012 1114 9042!1114 9042[1145 9073 1198 9073!1198 9073[1242 9073 1269 9060!1269 9060[1296 9048 1322 9016!1322 9016|1324 9016!1324 9016|1344 9066!1344 9066|1415 9066!1314 8925[1314 8958 1293
 8978!1293 8978[1272 8999 1237 8999!1237 8999[1187 8999 1187 8956!1187 8956[1187 8926 1209 8911!1209 8911[1231 8897 1275 8895!1275 8895|1314 8894!1314 8894|1314 8925!624 9427|624 9315!624 9315[624 9283 608 9268!608 9268[592 9253 561 9253
!561 9253[543 9253 529 9260!529 9260[514 9267 507 9280!507 9280|505 9280!505 9280|506 9184!506 9184|481 9184!481 9184|481 9427!481 9427|506 9427!506 9427|506 9337!506 9337[506 9304 519 9289!519 9289[531 9275 558 9275!558 9275[579 9275
 588 9285!588 9285[598 9295 598 9316!598 9316|598 9427!598 9427|624 9427!801 9427|801 9310!801 9310[801 9280 786 9267!786 9267[772 9253 741 9253!741 9253[726 9253 711 9257!711 9257[696 9261 683 9268!683 9268|691 9287!691 9287[718 9274
 739 9274!739 9274[758 9274 767 9284!767 9284[776 9294 776 9314!776 9314|776 9324!776 9324|747 9325!747 9325[664 9328 664 9380!664 9380[664 9404 678 9417!678 9417[693 9430 718 9430!718 9430[737 9430 750 9425!750 9425[763 9419 775 9403
!775 9403|777 9403!777 9403|782 9427!782 9427|801 9427!699 9401[691 9394 691 9380!691 9380[691 9362 705 9354!705 9354[718 9345 749 9344!749 9344|775 9343!775 9343|775 9358!775 9358[775 9382 761 9395!761 9395[747 9409 723 9409!723 9409
[708 9409 699 9401!1489 9427|1489 9310!1489 9310[1489 9280 1474 9267!1474 9267[1460 9253 1429 9253!1429 9253[1414 9253 1399 9257!1399 9257[1384 9261 1371 9268!1371 9268|1379 9287!1379 9287[1406 9274 1427 9274!1427 9274[1446 9274 1455
 9284!1455 9284[1464 9294 1464 9314!1464 9314|1464 9324!1464 9324|1435 9325!1435 9325[1352 9328 1352 9380!1352 9380[1352 9404 1366 9417!1366 9417[1381 9430 1406 9430!1406 9430[1425 9430 1438 9425!1438 9425[1451 9419 1463 9403!1463 9403
|1465 9403!1465 9403|1470 9427!1470 9427|1489 9427!1287 9222[1291 9227 1298 9227!1298 9227[1304 9227 1308 9222!1308 9222[1313 9218 1313 9209!1313 9209[1313 9201 1308 9196!1308 9196[1304 9192 1298 9192!1298 9192[1291 9192 1287 9196!1287
 9196[1282 9200 1282 9209!1282 9209[1282 9218 1287 9222!1310 9256|1285 9256!1285 9256|1285 9427!1285 9427|1310 9427!1310 9427|1310 9256!1387 9401[1379 9394 1379 9380!1379 9380[1379 9362 1393 9354!1393 9354[1406 9345 1437 9344!1437 9344
|1463 9343!1463 9343|1463 9358!1463 9358[1463 9382 1449 9395!1449 9395[1435 9409 1411 9409!1411 9409[1396 9409 1387 9401!953 9352[943 9341 912 9330!912 9330[890 9321 882 9317!882 9317[874 9313 871 9308!871 9308[867 9303 867 9296!867 9296
[867 9286 877 9280!877 9280[886 9274 904 9274!904 9274[925 9274 951 9285!951 9285|960 9264!960 9264[934 9253 906 9253!906 9253[877 9253 860 9265!860 9265[843 9277 843 9298!843 9298[843 9310 848 9318!848 9318[852 9326 863 9333!863 9333
[873 9340 896 9349!896 9349[922 9358 930 9365!930 9365[939 9372 939 9382!939 9382[939 9396 928 9402!928 9402[917 9409 897 9409!897 9409[884 9409 870 9405!870 9405[855 9402 843 9395!843 9395|843 9419!843 9419[862 9430 896 9430!896 9430
[928 9430 946 9417!946 9417[964 9404 964 9380!964 9380[964 9363 953 9352!1209 9427|1230 9427!1230 9427|1230 9184!1230 9184|1204 9184!1204 9184|1204 9266!1204 9266|1205 9278!1205 9278|1203 9278!1203 9278[1185 9253 1150 9253!1150 9253[1116
 9253 1098 9276!1098 9276[1079 9300 1079 9342!1079 9342[1079 9384 1098 9407!1098 9407[1116 9430 1150 9430!1150 9430[1186 9430 1204 9404!1204 9404|1205 9404!1205 9404|1209 9427!1118 9392[1106 9375 1106 9342!1106 9342[1106 9310 1118 9292
!1118 9292[1130 9274 1153 9274!1153 9274[1179 9274 1192 9290!1192 9290[1204 9305 1204 9342!1204 9342|1204 9347!1204 9347[1204 9380 1192 9394!1192 9394[1180 9408 1153 9408!1153 9408[1130 9408 1118 9392"/>
                      </edges>
                    </DOMShape>
                  </members>
                </DOMGroup>
              </elements>
            </DOMFrame>
            <DOMFrame index="1" keyMode="9728">
              <elements>
                <DOMGroup>
                  <matrix>
                    <Matrix tx="-24.05" ty="-429.05"/>
                  </matrix>
                  <members>
                    <DOMShape>
                      <matrix>
                        <Matrix tx="-24.05" ty="-429.05"/>
                      </matrix>
                      <fills>
                        <FillStyle index="1">
                          <SolidColor color="#303030"/>
                        </FillStyle>
                      </fills>
                      <edges>
                        <Edge fillStyle0="1" edges="
!1662 8707S1[1632 8726 1615 8757!1615 8757|1610 8757!1610 8757|1595 8695!1595 8695|1518 8695!1518 8695|1518 9066!1518 9066|1619 9066!1619 9066|1619 8877!1619 8877[1619 8832 1647 8807!1647 8807[1674 8782 1722 8782!1722 8782|1752 8786!1752
 8786|1760 8691!1760 8691|1725 8688!1725 8688[1691 8688 1662 8707!2133 9066|2133 8819!2133 8819[2133 8752 2093 8720!2093 8720[2053 8687 1978 8687!1978 8687[1900 8687 1836 8721!1836 8721|1870 8789!1870 8789[1930 8762 1974 8762!1974 8762
[2032 8762 2032 8819!2032 8819|2032 8835!2032 8835|1968 8837!1968 8837[1884 8840 1843 8868!1843 8868[1802 8896 1802 8955!1802 8955[1802 9012 1832 9042!1832 9042[1863 9073 1916 9073!1916 9073[1960 9073 1987 9060!1987 9060[2014 9048 2040
 9016!2040 9016|2042 9016!2042 9016|2062 9066!2062 9066|2133 9066!2032 8925[2032 8958 2011 8978!2011 8978[1990 8999 1955 8999!1955 8999[1905 8999 1905 8956!1905 8956[1905 8926 1927 8911!1927 8911[1949 8897 1993 8895!1993 8895|2032 8894
!2032 8894|2032 8925!2131 9428[2143 9425 2156 9419!2156 9419|2156 9396!2156 9396[2129 9407 2102 9407!2102 9407[2076 9407 2061 9392!2061 9392[2047 9376 2046 9346!2046 9346|2164 9346!2164 9346|2164 9330!2164 9330[2164 9295 2145 9274!2145
 9274[2126 9253 2094 9253!2094 9253[2060 9253 2039 9277!2039 9277[2019 9301 2019 9343!2019 9343[2019 9384 2041 9407!2041 9407[2063 9430 2101 9430!2101 9430[2118 9430 2131 9428!2125 9287[2136 9300 2136 9325!2136 9325|2046 9325!2046 9325
[2049 9301 2061 9288!2061 9288[2073 9274 2094 9274!2094 9274[2114 9274 2125 9287!2307 9352[2297 9341 2266 9330!2266 9330[2244 9321 2236 9317!2236 9317[2228 9313 2225 9308!2225 9308[2221 9303 2221 9296!2221 9296[2221 9286 2231 9280!2231
 9280[2240 9274 2258 9274!2258 9274[2279 9274 2305 9285!2305 9285|2314 9264!2314 9264[2288 9253 2260 9253!2260 9253[2231 9253 2214 9265!2214 9265[2197 9277 2197 9298!2197 9298[2197 9310 2202 9318!2202 9318[2206 9326 2217 9333!2217 9333
[2227 9340 2250 9349!2250 9349[2276 9358 2284 9365!2284 9365[2293 9372 2293 9382!2293 9382[2293 9396 2282 9402!2282 9402[2271 9409 2251 9409!2251 9409[2238 9409 2224 9405!2224 9405[2209 9402 2197 9395!2197 9395|2197 9419!2197 9419[2216
 9430 2250 9430!2250 9430[2282 9430 2300 9417!2300 9417[2318 9404 2318 9380!2318 9380[2318 9363 2307 9352!1840 9428[1852 9425 1865 9419!1865 9419|1865 9396!1865 9396[1838 9407 1811 9407!1811 9407[1785 9407 1770 9392!1770 9392[1756 9376
 1755 9346!1755 9346|1873 9346!1873 9346|1873 9330!1873 9330[1873 9295 1854 9274!1854 9274[1835 9253 1803 9253!1803 9253[1769 9253 1748 9277!1748 9277[1728 9301 1728 9343!1728 9343[1728 9384 1750 9407!1750 9407[1772 9430 1810 9430!1810
 9430[1827 9430 1840 9428!1567 9279|1566 9279!1566 9279|1567 9184!1567 9184|1542 9184!1542 9184|1542 9427!1542 9427|1560 9427!1560 9427|1566 9405!1566 9405|1567 9405!1567 9405[1577 9418 1591 9424!1591 9424[1604 9430 1621 9430!1621 9430
[1655 9430 1674 9407!1674 9407[1692 9383 1692 9341!1692 9341[1692 9299 1674 9276!1674 9276[1655 9253 1621 9253!1621 9253[1586 9253 1567 9279!1654 9291[1665 9307 1665 9341!1665 9341[1665 9374 1654 9391!1654 9391[1642 9408 1618 9408!1618
 9408[1592 9408 1579 9393!1579 9393[1567 9377 1567 9341!1567 9341[1567 9305 1579 9290!1579 9290[1591 9275 1617 9275!1617 9275[1642 9275 1654 9291!1834 9287[1845 9300 1845 9325!1845 9325|1755 9325!1755 9325[1758 9301 1770 9288!1770 9288
[1782 9274 1803 9274!1803 9274[1823 9274 1834 9287!1952 9400[1944 9392 1944 9377!1944 9377|1944 9276!1944 9276|1994 9276!1994 9276|1994 9256!1994 9256|1944 9256!1944 9256|1944 9216!1944 9216|1929 9216!1929 9216|1918 9253!1918 9253|1894
 9263!1894 9263|1894 9276!1894 9276|1918 9276!1918 9276|1918 9378!1918 9378[1918 9430 1968 9430!1968 9430|1983 9429!1983 9429|1995 9425!1995 9425|1995 9406!1995 9406|1985 9408!1985 9408|1972 9409!1972 9409[1959 9409 1952 9400!885 8795
|1054 8581!1054 8581|940 8581!940 8581|768 8803!768 8803|768 8581!768 8581|665 8581!665 8581|665 9066!665 9066|768 9066!768 9066|768 8893!768 8893|812 8861!812 8861|939 9066!939 9066|1056 9066!1056 9066|885 8795!1415 9066|1415 8819!1415
 8819[1415 8752 1375 8720!1375 8720[1335 8687 1260 8687!1260 8687[1182 8687 1118 8721!1118 8721|1152 8789!1152 8789[1212 8762 1256 8762!1256 8762[1314 8762 1314 8819!1314 8819|1314 8835!1314 8835|1250 8837!1250 8837[1166 8840 1125 8868
!1125 8868[1084 8896 1084 8955!1084 8955[1084 9012 1114 9042!1114 9042[1145 9073 1198 9073!1198 9073[1242 9073 1269 9060!1269 9060[1296 9048 1322 9016!1322 9016|1324 9016!1324 9016|1344 9066!1344 9066|1415 9066!1314 8925[1314 8958 1293
 8978!1293 8978[1272 8999 1237 8999!1237 8999[1187 8999 1187 8956!1187 8956[1187 8926 1209 8911!1209 8911[1231 8897 1275 8895!1275 8895|1314 8894!1314 8894|1314 8925!624 9427|624 9315!624 9315[624 9283 608 9268!608 9268[592 9253 561 9253
!561 9253[543 9253 529 9260!529 9260[514 9267 507 9280!507 9280|505 9280!505 9280|506 9184!506 9184|481 9184!481 9184|481 9427!481 9427|506 9427!506 9427|506 9337!506 9337[506 9304 519 9289!519 9289[531 9275 558 9275!558 9275[579 9275
 588 9285!588 9285[598 9295 598 9316!598 9316|598 9427!598 9427|624 9427!801 9427|801 9310!801 9310[801 9280 786 9267!786 9267[772 9253 741 9253!741 9253[726 9253 711 9257!711 9257[696 9261 683 9268!683 9268|691 9287!691 9287[718 9274
 739 9274!739 9274[758 9274 767 9284!767 9284[776 9294 776 9314!776 9314|776 9324!776 9324|747 9325!747 9325[664 9328 664 9380!664 9380[664 9404 678 9417!678 9417[693 9430 718 9430!718 9430[737 9430 750 9425!750 9425[763 9419 775 9403
!775 9403|777 9403!777 9403|782 9427!782 9427|801 9427!699 9401[691 9394 691 9380!691 9380[691 9362 705 9354!705 9354[718 9345 749 9344!749 9344|775 9343!775 9343|775 9358!775 9358[775 9382 761 9395!761 9395[747 9409 723 9409!723 9409
[708 9409 699 9401!1489 9427|1489 9310!1489 9310[1489 9280 1474 9267!1474 9267[1460 9253 1429 9253!1429 9253[1414 9253 1399 9257!1399 9257[1384 9261 1371 9268!1371 9268|1379 9287!1379 9287[1406 9274 1427 9274!1427 9274[1446 9274 1455
 9284!1455 9284[1464 9294 1464 9314!1464 9314|1464 9324!1464 9324|1435 9325!1435 9325[1352 9328 1352 9380!1352 9380[1352 9404 1366 9417!1366 9417[1381 9430 1406 9430!1406 9430[1425 9430 1438 9425!1438 9425[1451 9419 1463 9403!1463 9403
|1465 9403!1465 9403|1470 9427!1470 9427|1489 9427!1287 9222[1291 9227 1298 9227!1298 9227[1304 9227 1308 9222!1308 9222[1313 9218 1313 9209!1313 9209[1313 9201 1308 9196!1308 9196[1304 9192 1298 9192!1298 9192[1291 9192 1287 9196!1287
 9196[1282 9200 1282 9209!1282 9209[1282 9218 1287 9222!1310 9256|1285 9256!1285 9256|1285 9427!1285 9427|1310 9427!1310 9427|1310 9256!1387 9401[1379 9394 1379 9380!1379 9380[1379 9362 1393 9354!1393 9354[1406 9345 1437 9344!1437 9344
|1463 9343!1463 9343|1463 9358!1463 9358[1463 9382 1449 9395!1449 9395[1435 9409 1411 9409!1411 9409[1396 9409 1387 9401!953 9352[943 9341 912 9330!912 9330[890 9321 882 9317!882 9317[874 9313 871 9308!871 9308[867 9303 867 9296!867 9296
[867 9286 877 9280!877 9280[886 9274 904 9274!904 9274[925 9274 951 9285!951 9285|960 9264!960 9264[934 9253 906 9253!906 9253[877 9253 860 9265!860 9265[843 9277 843 9298!843 9298[843 9310 848 9318!848 9318[852 9326 863 9333!863 9333
[873 9340 896 9349!896 9349[922 9358 930 9365!930 9365[939 9372 939 9382!939 9382[939 9396 928 9402!928 9402[917 9409 897 9409!897 9409[884 9409 870 9405!870 9405[855 9402 843 9395!843 9395|843 9419!843 9419[862 9430 896 9430!896 9430
[928 9430 946 9417!946 9417[964 9404 964 9380!964 9380[964 9363 953 9352!1209 9427|1230 9427!1230 9427|1230 9184!1230 9184|1204 9184!1204 9184|1204 9266!1204 9266|1205 9278!1205 9278|1203 9278!1203 9278[1185 9253 1150 9253!1150 9253[1116
 9253 1098 9276!1098 9276[1079 9300 1079 9342!1079 9342[1079 9384 1098 9407!1098 9407[1116 9430 1150 9430!1150 9430[1186 9430 1204 9404!1204 9404|1205 9404!1205 9404|1209 9427!1118 9392[1106 9375 1106 9342!1106 9342[1106 9310 1118 9292
!1118 9292[1130 9274 1153 9274!1153 9274[1179 9274 1192 9290!1192 9290[1204 9305 1204 9342!1204 9342|1204 9347!1204 9347[1204 9380 1192 9394!1192 9394[1180 9408 1153 9408!1153 9408[1130 9408 1118 9392"/>
                      </edges>
                    </DOMShape>
                  </members>
                </DOMGroup>
              </elements>
            </DOMFrame>
            <DOMFrame index="2" keyMode="9728">
              <elements>
                <DOMGroup>
                  <matrix>
                    <Matrix tx="-21.95" ty="-429.05"/>
                  </matrix>
                  <members>
                    <DOMShape>
                      <matrix>
                        <Matrix tx="-21.95" ty="-429.05"/>
                      </matrix>
                      <fills>
                        <FillStyle index="1">
                          <SolidColor color="#303030"/>
                        </FillStyle>
                      </fills>
                      <edges>
                        <Edge fillStyle0="1" edges="
!1662 8707S1[1632 8726 1615 8757!1615 8757|1610 8757!1610 8757|1595 8695!1595 8695|1518 8695!1518 8695|1518 9066!1518 9066|1619 9066!1619 9066|1619 8877!1619 8877[1619 8832 1647 8807!1647 8807[1674 8782 1722 8782!1722 8782|1752 8786!1752
 8786|1760 8691!1760 8691|1725 8688!1725 8688[1691 8688 1662 8707!2133 9066|2133 8819!2133 8819[2133 8752 2093 8720!2093 8720[2053 8687 1978 8687!1978 8687[1900 8687 1836 8721!1836 8721|1870 8789!1870 8789[1930 8762 1974 8762!1974 8762
[2032 8762 2032 8819!2032 8819|2032 8835!2032 8835|1968 8837!1968 8837[1884 8840 1843 8868!1843 8868[1802 8896 1802 8955!1802 8955[1802 9012 1832 9042!1832 9042[1863 9073 1916 9073!1916 9073[1960 9073 1987 9060!1987 9060[2014 9048 2040
 9016!2040 9016|2042 9016!2042 9016|2062 9066!2062 9066|2133 9066!2032 8925[2032 8958 2011 8978!2011 8978[1990 8999 1955 8999!1955 8999[1905 8999 1905 8956!1905 8956[1905 8926 1927 8911!1927 8911[1949 8897 1993 8895!1993 8895|2032 8894
!2032 8894|2032 8925!2154 9426[2146 9418 2146 9403!2146 9403|2146 9302!2146 9302|2196 9302!2196 9302|2196 9282!2196 9282|2146 9282!2146 9282|2146 9242!2146 9242|2131 9242!2131 9242|2120 9279!2120 9279|2096 9289!2096 9289|2096 9302!2096
 9302|2120 9302!2120 9302|2120 9404!2120 9404[2120 9456 2170 9456!2170 9456|2185 9455!2185 9455|2197 9451!2197 9451|2197 9432!2197 9432|2187 9434!2187 9434|2174 9435!2174 9435[2161 9435 2154 9426!2042 9454[2054 9451 2067 9445!2067 9445
|2067 9422!2067 9422[2040 9433 2013 9433!2013 9433[1987 9433 1972 9418!1972 9418[1958 9402 1957 9372!1957 9372|2075 9372!2075 9372|2075 9356!2075 9356[2075 9321 2056 9300!2056 9300[2037 9279 2005 9279!2005 9279[1971 9279 1950 9303!1950
 9303[1930 9327 1930 9369!1930 9369[1930 9410 1952 9433!1952 9433[1974 9456 2012 9456!2012 9456[2029 9456 2042 9454!2036 9313[2047 9326 2047 9351!2047 9351|1957 9351!1957 9351[1960 9327 1972 9314!1972 9314[1984 9300 2005 9300!2005 9300
[2025 9300 2036 9313!2327 9313[2338 9326 2338 9351!2338 9351|2248 9351!2248 9351[2251 9327 2263 9314!2263 9314[2275 9300 2296 9300!2296 9300[2316 9300 2327 9313!2509 9378[2499 9367 2468 9356!2468 9356[2446 9347 2438 9343!2438 9343[2430
 9339 2427 9334!2427 9334[2423 9329 2423 9322!2423 9322[2423 9312 2433 9306!2433 9306[2442 9300 2460 9300!2460 9300[2481 9300 2507 9311!2507 9311|2516 9290!2516 9290[2490 9279 2462 9279!2462 9279[2433 9279 2416 9291!2416 9291[2399 9303
 2399 9324!2399 9324[2399 9336 2404 9344!2404 9344[2408 9352 2419 9359!2419 9359[2429 9366 2452 9375!2452 9375[2478 9384 2486 9391!2486 9391[2495 9398 2495 9408!2495 9408[2495 9422 2484 9428!2484 9428[2473 9435 2453 9435!2453 9435[2440
 9435 2426 9431!2426 9431[2411 9428 2399 9421!2399 9421|2399 9445!2399 9445[2418 9456 2452 9456!2452 9456[2484 9456 2502 9443!2502 9443[2520 9430 2520 9406!2520 9406[2520 9389 2509 9378!2333 9454[2345 9451 2358 9445!2358 9445|2358 9422
!2358 9422[2331 9433 2304 9433!2304 9433[2278 9433 2263 9418!2263 9418[2249 9402 2248 9372!2248 9372|2366 9372!2366 9372|2366 9356!2366 9356[2366 9321 2347 9300!2347 9300[2328 9279 2296 9279!2296 9279[2262 9279 2241 9303!2241 9303[2221
 9327 2221 9369!2221 9369[2221 9410 2243 9433!2243 9433[2265 9456 2303 9456!2303 9456[2320 9456 2333 9454!1769 9305|1768 9305!1768 9305|1769 9210!1769 9210|1744 9210!1744 9210|1744 9453!1744 9453|1762 9453!1762 9453|1768 9431!1768 9431
|1769 9431!1769 9431[1779 9444 1793 9450!1793 9450[1806 9456 1823 9456!1823 9456[1857 9456 1876 9433!1876 9433[1894 9409 1894 9367!1894 9367[1894 9325 1876 9302!1876 9302[1857 9279 1823 9279!1823 9279[1788 9279 1769 9305!1691 9453|1691
 9336!1691 9336[1691 9306 1676 9293!1676 9293[1662 9279 1631 9279!1631 9279[1616 9279 1601 9283!1601 9283[1586 9287 1573 9294!1573 9294|1581 9313!1581 9313[1608 9300 1629 9300!1629 9300[1648 9300 1657 9310!1657 9310[1666 9320 1666 9340
!1666 9340|1666 9350!1666 9350|1637 9351!1637 9351[1554 9354 1554 9406!1554 9406[1554 9430 1568 9443!1568 9443[1583 9456 1608 9456!1608 9456[1627 9456 1640 9451!1640 9451[1653 9445 1665 9429!1665 9429|1667 9429!1667 9429|1672 9453!1672
 9453|1691 9453!1589 9427[1581 9420 1581 9406!1581 9406[1581 9388 1595 9380!1595 9380[1608 9371 1639 9370!1639 9370|1665 9369!1665 9369|1665 9384!1665 9384[1665 9408 1651 9421!1651 9421[1637 9435 1613 9435!1613 9435[1598 9435 1589 9427
!1856 9317[1867 9333 1867 9367!1867 9367[1867 9400 1856 9417!1856 9417[1844 9434 1820 9434!1820 9434[1794 9434 1781 9419!1781 9419[1769 9403 1769 9367!1769 9367[1769 9331 1781 9316!1781 9316[1793 9301 1819 9301!1819 9301[1844 9301 1856
 9317!885 8795|1054 8581!1054 8581|940 8581!940 8581|768 8803!768 8803|768 8581!768 8581|665 8581!665 8581|665 9066!665 9066|768 9066!768 9066|768 8893!768 8893|812 8861!812 8861|939 9066!939 9066|1056 9066!1056 9066|885 8795!1415 9066
|1415 8819!1415 8819[1415 8752 1375 8720!1375 8720[1335 8687 1260 8687!1260 8687[1182 8687 1118 8721!1118 8721|1152 8789!1152 8789[1212 8762 1256 8762!1256 8762[1314 8762 1314 8819!1314 8819|1314 8835!1314 8835|1250 8837!1250 8837[1166
 8840 1125 8868!1125 8868[1084 8896 1084 8955!1084 8955[1084 9012 1114 9042!1114 9042[1145 9073 1198 9073!1198 9073[1242 9073 1269 9060!1269 9060[1296 9048 1322 9016!1322 9016|1324 9016!1324 9016|1344 9066!1344 9066|1415 9066!1314 8925
[1314 8958 1293 8978!1293 8978[1272 8999 1237 8999!1237 8999[1187 8999 1187 8956!1187 8956[1187 8926 1209 8911!1209 8911[1231 8897 1275 8895!1275 8895|1314 8894!1314 8894|1314 8925!576 9248[580 9253 587 9253!587 9253[593 9253 597 9248
!597 9248[602 9244 602 9235!602 9235[602 9227 597 9222!597 9222[593 9218 587 9218!587 9218[580 9218 576 9222!576 9222[571 9226 571 9235!571 9235[571 9244 576 9248!497 9426[489 9418 489 9403!489 9403|489 9302!489 9302|539 9302!539 9302
|539 9282!539 9282|489 9282!489 9282|489 9242!489 9242|474 9242!474 9242|463 9279!463 9279|439 9289!439 9289|439 9302!439 9302|463 9302!463 9302|463 9404!463 9404[463 9456 513 9456!513 9456|528 9455!528 9455|540 9451!540 9451|540 9432
!540 9432|530 9434!530 9434|517 9435!517 9435[504 9435 497 9426!599 9282|574 9282!574 9282|574 9453!574 9453|599 9453!599 9453|599 9282!756 9454[768 9451 781 9445!781 9445|781 9422!781 9422[754 9433 727 9433!727 9433[701 9433 686 9418
!686 9418[672 9402 671 9372!671 9372|789 9372!789 9372|789 9356!789 9356[789 9321 770 9300!770 9300[751 9279 719 9279!719 9279[685 9279 664 9303!664 9303[644 9327 644 9369!644 9369[644 9410 666 9433!666 9433[688 9456 726 9456!726 9456
[743 9456 756 9454!750 9313[761 9326 761 9351!761 9351|671 9351!671 9351[674 9327 686 9314!686 9314[698 9300 719 9300!719 9300[739 9300 750 9313!1411 9453|1432 9453!1432 9453|1432 9210!1432 9210|1406 9210!1406 9210|1406 9292!1406 9292
|1407 9304!1407 9304|1405 9304!1405 9304[1387 9279 1352 9279!1352 9279[1318 9279 1300 9302!1300 9302[1281 9326 1281 9368!1281 9368[1281 9410 1300 9433!1300 9433[1318 9456 1352 9456!1352 9456[1388 9456 1406 9430!1406 9430|1407 9430!1407
 9430|1411 9453!1320 9418[1308 9401 1308 9368!1308 9368[1308 9336 1320 9318!1320 9318[1332 9300 1355 9300!1355 9300[1381 9300 1394 9316!1394 9316[1406 9331 1406 9368!1406 9368|1406 9373!1406 9373[1406 9406 1394 9420!1394 9420[1382 9434
 1355 9434!1355 9434[1332 9434 1320 9418!1489 9248[1493 9253 1500 9253!1500 9253[1506 9253 1510 9248!1510 9248[1515 9244 1515 9235!1515 9235[1515 9227 1510 9222!1510 9222[1506 9218 1500 9218!1500 9218[1493 9218 1489 9222!1489 9222[1484
 9226 1484 9235!1484 9235[1484 9244 1489 9248!1512 9282|1487 9282!1487 9282|1487 9453!1487 9453|1512 9453!1512 9453|1512 9282!976 9453|976 9341!976 9341[976 9308 960 9294!960 9294[944 9279 913 9279!913 9279[896 9279 881 9286!881 9286
[867 9293 859 9305!859 9305|858 9305!858 9305|854 9282!854 9282|833 9282!833 9282|833 9453!833 9453|858 9453!858 9453|858 9363!858 9363[858 9330 871 9315!871 9315[883 9301 910 9301!910 9301[931 9301 940 9311!940 9311[950 9321 950 9342
!950 9342|950 9453!950 9453|976 9453!1125 9313[1136 9326 1136 9351!1136 9351|1046 9351!1046 9351[1049 9327 1061 9314!1061 9314[1073 9300 1094 9300!1094 9300[1114 9300 1125 9313!1131 9454[1143 9451 1156 9445!1156 9445|1156 9422!1156 9422
[1129 9433 1102 9433!1102 9433[1076 9433 1061 9418!1061 9418[1047 9402 1046 9372!1046 9372|1164 9372!1164 9372|1164 9356!1164 9356[1164 9321 1145 9300!1145 9300[1126 9279 1094 9279!1094 9279[1060 9279 1039 9303!1039 9303[1019 9327 1019
 9369!1019 9369[1019 9410 1041 9433!1041 9433[1063 9456 1101 9456!1101 9456[1118 9456 1131 9454"/>
                      </edges>
                    </DOMShape>
                  </members>
                </DOMGroup>
              </elements>
            </DOMFrame>
          </frames>
        </DOMLayer>
      </layers>
    </DOMTimeline>
  </timeline>
</DOMSymbolItem>